cloverspace/__init__.py
cloverspace/__main__.py
cloverspace/client.py
cloverspace/api/__init__.py
cloverspace/api/request_manager.py
cloverspace/api/headers/__init__.py
cloverspace/api/headers/base_headers_provider.py
cloverspace/api/headers/headers_provider.py
cloverspace/api/util/__init__.py
cloverspace/api/util/copy_to_buffer_writer.py
cloverspace/enum/__init__.py
cloverspace/enum/auth_purpose.py
cloverspace/enum/auth_type.py
cloverspace/enum/chat_message_type.py
cloverspace/enum/chat_query_type.py
cloverspace/enum/chat_thread_type.py
cloverspace/enum/circle_filter_type.py
cloverspace/enum/circle_members_query_type.py
cloverspace/enum/comment_type.py
cloverspace/enum/content_region.py
cloverspace/enum/currency_type.py
cloverspace/enum/gender.py
cloverspace/enum/object_type.py
cloverspace/enum/party_query_type.py
cloverspace/enum/upload_target.py
cloverspace/enum/user_task_type.py
cloverspace/enum/ws_event_type.py
cloverspace/error/__init__.py
cloverspace/error/classes.py
cloverspace/model/__init__.py
cloverspace/model/account.py
cloverspace/model/blocked_item_wrapper.py
cloverspace/model/blog.py
cloverspace/model/category.py
cloverspace/model/chat.py
cloverspace/model/chat_message.py
cloverspace/model/circle.py
cloverspace/model/comment.py
cloverspace/model/currency.py
cloverspace/model/default_background_media.py
cloverspace/model/dice.py
cloverspace/model/gift_box.py
cloverspace/model/link_info.py
cloverspace/model/media.py
cloverspace/model/member_title.py
cloverspace/model/party.py
cloverspace/model/poll.py
cloverspace/model/qi_vote_full_info.py
cloverspace/model/qi_vote_info.py
cloverspace/model/reaction.py
cloverspace/model/rich_format.py
cloverspace/model/sticker.py
cloverspace/model/transfer_order.py
cloverspace/model/user.py
cloverspace/model/user_task.py
cloverspace/model/wallet.py
cloverspace/model/parse/__init__.py
cloverspace/model/parse/parseutils.py
cloverspace/model/response/__init__.py
cloverspace/model/response/auth_result.py
cloverspace-3.0.1.dist-info/METADATA
cloverspace-3.0.1.dist-info/WHEEL
cloverspace-3.0.1.dist-info/top_level.txt
cloverspace-3.0.1.dist-info/RECORD
