Metadata-Version: 2.4
Name: cloverspace
Version: 3.0.1
Summary: An asynchronous library for creating scripts and chatbots in Clover.Space;
Home-page: https://github.com/LixxRarin/Clover.Space/
Author: LixxRarin
Author-email: lixxrarin@gmail.com
Keywords: project-z,projectz,projz,bots,api,supersymlab,projz-bot,projz-bots,projz-api,cloverspace,clover-space
Requires-Python: >=3.7
Requires-Dist: aiohttp
Requires-Dist: aiofiles
Requires-Dist: ujson
Requires-Dist: dataclasses
Requires-Dist: dataclasses-json
Requires-Dist: python-dateutil
Requires-Dist: dill
Requires-Dist: python-magic
Dynamic: author
Dynamic: author-email
Dynamic: description
Dynamic: description-content-type
Dynamic: home-page
Dynamic: keywords
Dynamic: requires-dist
Dynamic: requires-python
Dynamic: summary
